LICENSE
README.md
setup.cfg
setup.py
diweir/__init__.py
diweir.egg-info/PKG-INFO
diweir.egg-info/SOURCES.txt
diweir.egg-info/dependency_links.txt
diweir.egg-info/entry_points.txt
diweir.egg-info/requires.txt
diweir.egg-info/top_level.txt
diweir.egg-info/zip-safe