Metadata-Version: 2.1
Name: diweir
Version: 0.1.0
Summary: Prepare control scripts for large scale Data Integration
Home-page: https://github.com/supratikchatterjee16/diweir
Author: Supratik Chatterjee
Author-email: supratikdevm96@gmail.com
License:                                  Apache License
Keywords: serp,bot,webscraping,scraping,search engine,package,python,crawler
Classifier: Programming Language :: Python :: 3
Classifier: Operating System :: OS Independent
License-File: LICENSE
